dict_codemasterpy/__init__.py
dict_codemasterpy/main.py
dict_codemasterpy-1.0.dist-info/METADATA
dict_codemasterpy-1.0.dist-info/WHEEL
dict_codemasterpy-1.0.dist-info/top_level.txt
dict_codemasterpy-1.0.dist-info/RECORD
