Metadata-Version: 2.1
Name: dict_codemasterpy
Version: 1.0
Requires-Dist: colorama>=0.4.6
